typedinterpolation.py
TypedInterpolation-1.0.0.dist-info/METADATA
TypedInterpolation-1.0.0.dist-info/WHEEL
TypedInterpolation-1.0.0.dist-info/top_level.txt
TypedInterpolation-1.0.0.dist-info/RECORD
