Metadata-Version: 2.1
Name: TypedInterpolation
Version: 1.0.0
Summary: Interpolations for configparser which uses ast.literal_eval.
Home-page: UNKNOWN
Author: Fink Dennis
Author-email: dennis.fink@c3l.lu
License: GPLv3+
Keywords: configparser interpolation typed
Platform: any
Classifier: Development Status :: 5 - Production/Stable
Classifier: Intended Audience :: Developers
Classifier: License :: OSI Approved :: GNU General Public License v3 or later (GPLv3+)
Classifier: Operating System :: OS Independent
Classifier: Programming Language :: Python
Classifier: Programming Language :: Python :: 3.5
Classifier: Topic :: Software Development
Classifier: Topic :: Utilities
Classifier: Topic :: Other/Nonlisted Topic
